module_logic.v
module module_logic #(
    parameter WIDTH     = 32
)(
    input [WIDTH - 1:0] alu_a,
    input [WIDTH - 1:0] alu_b,
    input [4:0]         alu_op,
    output[WIDTH - 1:0] alu_result
);

    reg [WIDTH - 1:0] result_r;

    // localparam : chính là hằng số (parameter) cục bộ
    localparam gAND             = 4'b0001;
    localparam gOR              = 4'b0010;
    localparam gNOT             = 4'b0011;
    localparam gXOR             = 4'b0100;
    localparam gNAND            = 4'b0101;
    localparam gNOR             = 4'b0110;

    localparam SHIFT_RIGHT      = 4'b0111;
    localparam SHIFT_RIGHT_ARITH= 4'b1000;
    localparam SHIFT_LEFT       = 4'b1001;

    localparam COMPARE          = 4'b1010;
    localparam BIGGER           = 4'b1011;
    localparam SMALLER          = 4'b1100;
 

    reg [31:16] shift_right_fill_r;
    reg [WIDTH-1:0] shift_right_1_r;
    reg [WIDTH-1:0] shift_right_2_r;
    reg [WIDTH-1:0] shift_right_4_r;
    reg [WIDTH-1:0] shift_right_8_r;

    reg [WIDTH-1:0] shift_left_1_r;
    reg [WIDTH-1:0] shift_left_2_r;
    reg [WIDTH-1:0] shift_left_4_r;
    reg [WIDTH-1:0] shift_left_8_r;

    // các cổng logic
    always @(alu_a or alu_b or alu_op) begin
        case(alu_op)
            gAND: 
                begin
                    result_r = alu_a & alu_b;
                end
            gOR:
                begin
                    result_r = alu_a | alu_b;
                end
            gNOT:
                begin
                    result_r = ~alu_a;
                end
            gXOR:
                begin
                    result_r = ~(alu_a | alu_b);
                end
            gNAND:
                begin
                    result_r = ~(alu_a & alu_b);
                end
            gNOR:
                begin
                    result_r = (~alu_a&alu_b) | (~alu_b&alu_a);
                end
            // dịch trái
            SHIFT_LEFT:
                begin
                    if(alu_b[0]==1'b1)
                        shift_left_1_r = {alu_a[30:0],1'b0};
                    else
                        shift_left_1_r = alu_a;

                    if(alu_b[1]==1'b1)
                        shift_left_2_r ={shift_left_1_r[29:0],2'b0};
                    else   
                        shift_left_2_r = shift_left_1_r;
                    
                    if(alu_b[2]==1'b1)
                        shift_left_4_r ={shift_left_2_r[27:0],4'b0000};
                    else    
                        shift_left_4_r = shift_left_2_r;

                    if(alu_b[3]==1'b1)
                        shift_left_8_r ={shift_left_8_r[23:0],8'b00000000};
                    else
                        shift_left_8_r =shift_left_4_r;

                    if(alu_b[4]==1'b1)
                        result_r = {shift_left_8_r[15:0],16'b0000000000000000};
                    else
                        result_r = shift_left_8_r;
                end

            SHIFT_RIGHT, SHIFT_RIGHT_ARITH:
                begin
                    if(alu_a[31] == 1'b1 && alu_op == SHIFT_RIGHT_ARITH)
                        shift_right_fill_r = 16'b1111111111111111;
                    else
                        shift_right_fill_r = 16'b0000000000000000;

                    if (alu_b[0] == 1'b1)
                        shift_right_1_r = {shift_right_fill_r[31],alu_a[31:1]};
                    else
                        shift_right_1_r = alu_a;
                    
                    if (alu_b[1] == 1'b1)
                        shift_right_2_r = {shift_right_fill_r[31:30],shift_right_1_r[31:2]};
                    else 
                        shift_right_2_r = shift_right_1_r;
                    
                    if (alu_b[2] == 1'b1)
                        shift_right_4_r = {shift_right_fill_r[31:28],shift_right_2_r[31:4]};
                    else
                        shift_right_4_r = shift_right_2_r;

                    if (alu_b[3] == 1'b1)
                        shift_right_8_r = {shift_right_fill_r[31:24],shift_right_4_r[31:8]};
                    else    
                        shift_right_8_r = shift_right_4_r;

                    if(alu_b [4] == 1'b1)
                        result_r = {shift_right_fill_r[31:16],shift_right_8_r[31:16]};
                    else
                        result_r = shift_right_8_r;


                end
            COMPARE :
                begin
                    result_r = (alu_a == alu_b) ? 32'b1 : 32'b0;
                end
            BIGGER :
                begin
                    result_r = (alu_a > alu_b) ? 32'b1 : 32'b0;
                end
            SMALLER :
                begin
                    result_r = (alu_a < alu_b) ? 32'b1 : 32'b0;
                end

        default:
            begin
                result_r <= 32'b0;
            end
        endcase
    end
    // so sánh
    assign alu_result = result_r;

endmodule

tb_module_logic.v
`timescale 1ns / 1ps
`include "module_logic.v"
module tb_module_logic;

    // Define the WIDTH parameter for the testbench and the DUT
    parameter WIDTH = 32;

    // Inputs to the DUT (Device Under Test)
    reg [WIDTH - 1:0] alu_a;
    reg [WIDTH - 1:0] alu_b;
    reg [4:0]         alu_op; // Keeping 5 bits for alu_op as in your original module

    // Output from the DUT
    wire [WIDTH - 1:0] alu_result;

    // Localparams for operations (matching your original values, adjusted for 5-bit alu_op if needed, otherwise this is fine)
    // IMPORTANT: Make sure these match the ones inside your module_logic
    localparam gAND             = 5'b00001; // Changed to 5-bit to match alu_op width
    localparam gOR              = 5'b00010;
    localparam gNOT             = 5'b00011;
    localparam gXOR             = 5'b00100;
    localparam gNAND            = 5'b00101;
    localparam gNOR             = 5'b00110;

    localparam SHIFT_RIGHT      = 5'b00111;
    localparam SHIFT_RIGHT_ARITH= 5'b01000;
    localparam SHIFT_LEFT       = 5'b01001;

    localparam COMPARE          = 5'b01010;
    localparam BIGGER           = 5'b01011;
    localparam SMALLER          = 5'b01100;

    // Instantiate the Device Under Test (DUT)
    module_logic #(
        .WIDTH(WIDTH)
    ) dut (
        .alu_a(alu_a),
        .alu_b(alu_b),
        .alu_op(alu_op),
        .alu_result(alu_result)
    );

    initial begin
        $dumpfile("tb_module_logic.vcd");
        $dumpvars(0, tb_module_logic);
    end


    // Initial block for test scenarios
    initial begin
        // Initialize inputs
        alu_a = 0;
        alu_b = 0;
        alu_op = 0;

        $display("--------------------------------------");
        $display("Starting module_logic Testbench");
        $display("Time | alu_a      | alu_b      | alu_op | alu_result");
        $display("--------------------------------------");

        // Test AND operation
        alu_a = 32'hAAAA_AAAA; // 1010...1010
        alu_b = 32'hFFFF_0000; // 1111...0000
        alu_op = gAND;
        #10 $display("%0t | %h | %h | %b | %h", $time, alu_a, alu_b, alu_op, alu_result);
        // Expected: alu_a & alu_b = 32'hAAAA_0000

        // Test OR operation
        alu_a = 32'hAAAA_AAAA;
        alu_b = 32'hFFFF_0000;
        alu_op = gOR;
        #10 $display("%0t | %h | %h | %b | %h", $time, alu_a, alu_b, alu_op, alu_result);
        // Expected: alu_a | alu_b = 32'hFFFF_AAAA

        // Test NOT operation
        alu_a = 32'hF0F0_F0F0;
        alu_b = 0; // Not used
        alu_op = gNOT;
        #10 $display("%0t | %h | %h | %b | %h", $time, alu_a, alu_b, alu_op, alu_result);
        // Expected: ~alu_a = 32'h0F0F_0F0F

        // Test XOR operation
        alu_a = 32'h1234_5678;
        alu_b = 32'h8765_4321;
        alu_op = gXOR;
        #10 $display("%0t | %h | %h | %b | %h", $time, alu_a, alu_b, alu_op, alu_result);
        // Expected: alu_a ^ alu_b = 32'h9551_1559

        // Test SHIFT_LEFT (logical)
        alu_a = 32'h0000_000F; // ...0000_1111
        alu_b = 5'd4; // Shift by 4
        alu_op = SHIFT_LEFT;
        #10 $display("%0t | %h | %h | %b | %h", $time, alu_a, alu_b, alu_op, alu_result);
        // Expected: 32'h0000_00F0

        // Test SHIFT_RIGHT (logical)
        alu_a = 32'hF000_0000; // 1111_0000...
        alu_b = 5'd4; // Shift by 4
        alu_op = SHIFT_RIGHT;
        #10 $display("%0t | %h | %h | %b | %h", $time, alu_a, alu_b, alu_op, alu_result);
        // Expected: 32'h0F00_0000

        // Test SHIFT_RIGHT_ARITH (positive number)
        alu_a = 32'h7000_0000; // Positive (MSB is 0)
        alu_b = 5'd4;
        alu_op = SHIFT_RIGHT_ARITH;
        #10 $display("%0t | %h | %h | %b | %h", $time, alu_a, alu_b, alu_op, alu_result);
        // Expected: 32'h0700_0000 (same as logical for positive)

        // Test SHIFT_RIGHT_ARITH (negative number)
        alu_a = 32'hFFFF_FF00; // Negative (MSB is 1)
        alu_b = 5'd4;
        alu_op = SHIFT_RIGHT_ARITH;
        #10 $display("%0t | %h | %h | %b | %h", $time, alu_a, alu_b, alu_op, alu_result);
        // Expected: 32'hFFFF_FFF0 (sign extension with 1s)

        // Test COMPARE (Equal)
        alu_a = 32'd100;
        alu_b = 32'd100;
        alu_op = COMPARE;
        #10 $display("%0t | %h | %h | %b | %h", $time, alu_a, alu_b, alu_op, alu_result);
        // Expected: 32'h0000_0001 (or 32'hFFFF_FFFF if you prefer all 1s for true)

        // Test COMPARE (Not Equal)
        alu_a = 32'd100;
        alu_b = 32'd99;
        alu_op = COMPARE;
        #10 $display("%0t | %h | %h | %b | %h", $time, alu_a, alu_b, alu_op, alu_result);
        // Expected: 32'h0000_0000

        // Test BIGGER
        alu_a = 32'd200;
        alu_b = 32'd150;
        alu_op = BIGGER;
        #10 $display("%0t | %h | %h | %b | %h", $time, alu_a, alu_b, alu_op, alu_result);
        // Expected: 32'h0000_0001

        // Test SMALLER
        alu_a = 32'd50;
        alu_b = 32'd100;
        alu_op = SMALLER;
        #10 $display("%0t | %h | %h | %b | %h", $time, alu_a, alu_b, alu_op, alu_result);
        // Expected: 32'h0000_0001

        // Default case
        alu_a = 0;
        alu_b = 0;
        alu_op = 5'b11111; // Undefined opcode
        #10 $display("%0t | %h | %h | %b | %h", $time, alu_a, alu_b, alu_op, alu_result);
        // Expected: 32'h0000_0000

        $display("--------------------------------------");
        $display("Testbench finished.");
        $finish; // End simulation
    end

endmodule

tb_module_logic.vcd
$date
	Sun Jun 29 10:00:30 2025
$end
$version
	Icarus Verilog
$end
$timescale
	1ps
$end
$scope module tb_module_logic $end
$var wire 32 ! alu_result [31:0] $end
$var parameter 5 " BIGGER $end
$var parameter 5 # COMPARE $end
$var parameter 5 $ SHIFT_LEFT $end
$var parameter 5 % SHIFT_RIGHT $end
$var parameter 5 & SHIFT_RIGHT_ARITH $end
$var parameter 5 ' SMALLER $end
$var parameter 32 ( WIDTH $end
$var parameter 5 ) gAND $end
$var parameter 5 * gNAND $end
$var parameter 5 + gNOR $end
$var parameter 5 , gNOT $end
$var parameter 5 - gOR $end
$var parameter 5 . gXOR $end
$var reg 32 / alu_a [31:0] $end
$var reg 32 0 alu_b [31:0] $end
$var reg 5 1 alu_op [4:0] $end
$scope module dut $end
$var wire 32 2 alu_a [31:0] $end
$var wire 32 3 alu_b [31:0] $end
$var wire 5 4 alu_op [4:0] $end
$var wire 32 5 alu_result [31:0] $end
$var parameter 4 6 BIGGER $end
$var parameter 4 7 COMPARE $end
$var parameter 4 8 SHIFT_LEFT $end
$var parameter 4 9 SHIFT_RIGHT $end
$var parameter 4 : SHIFT_RIGHT_ARITH $end
$var parameter 4 ; SMALLER $end
$var parameter 32 < WIDTH $end
$var parameter 4 = gAND $end
$var parameter 4 > gNAND $end
$var parameter 4 ? gNOR $end
$var parameter 4 @ gNOT $end
$var parameter 4 A gOR $end
$var parameter 4 B gXOR $end
$var reg 32 C result_r [31:0] $end
$var reg 32 D shift_left_1_r [31:0] $end
$var reg 32 E shift_left_2_r [31:0] $end
$var reg 32 F shift_left_4_r [31:0] $end
$var reg 32 G shift_left_8_r [31:0] $end
$var reg 32 H shift_right_1_r [31:0] $end
$var reg 32 I shift_right_2_r [31:0] $end
$var reg 32 J shift_right_4_r [31:0] $end
$var reg 32 K shift_right_8_r [31:0] $end
$var reg 16 L shift_right_fill_r [31:16] $end
$upscope $end
$upscope $end
$enddefinitions $end
$comment Show the parameter values. $end
$dumpall
b100 B
b10 A
b11 @
b110 ?
b101 >
b1 =
b100000 <
b1100 ;
b1000 :
b111 9
b1001 8
b1010 7
b1011 6
b100 .
b10 -
b11 ,
b110 +
b101 *
b1 )
b100000 (
b1100 '
b1000 &
b111 %
b1001 $
b1010 #
b1011 "
$end
#0
$dumpvars
bx L
bx K
bx J
bx I
bx H
bx G
bx F
bx E
bx D
b10101010101010100000000000000000 C
b10101010101010100000000000000000 5
b1 4
b11111111111111110000000000000000 3
b10101010101010101010101010101010 2
b1 1
b11111111111111110000000000000000 0
b10101010101010101010101010101010 /
b10101010101010100000000000000000 !
$end
#10000
b11111111111111111010101010101010 !
b11111111111111111010101010101010 5
b11111111111111111010101010101010 C
b10 1
b10 4
#20000
b1111000011110000111100001111 !
b1111000011110000111100001111 5
b1111000011110000111100001111 C
b11 1
b11 4
b0 0
b0 3
b11110000111100001111000011110000 /
b11110000111100001111000011110000 2
#30000
b1101000100010101010100010000110 !
b1101000100010101010100010000110 5
b1101000100010101010100010000110 C
b100 1
b100 4
b10000111011001010100001100100001 0
b10000111011001010100001100100001 3
b10010001101000101011001111000 /
b10010001101000101011001111000 2
#40000
b11110000 !
b11110000 5
b11110000 C
b11110000 G
b11110000 F
b1111 E
b1111 D
b1001 1
b1001 4
b100 0
b100 3
b1111 /
b1111 2
#50000
b1111000000000000000000000000 !
b1111000000000000000000000000 5
b1111000000000000000000000000 C
b1111000000000000000000000000 K
b1111000000000000000000000000 J
b11110000000000000000000000000000 I
b11110000000000000000000000000000 H
b0 L
b111 1
b111 4
b11110000000000000000000000000000 /
b11110000000000000000000000000000 2
#60000
b111000000000000000000000000 !
b111000000000000000000000000 5
b111000000000000000000000000 C
b111000000000000000000000000 K
b111000000000000000000000000 J
b1110000000000000000000000000000 I
b1110000000000000000000000000000 H
b1000 1
b1000 4
b1110000000000000000000000000000 /
b1110000000000000000000000000000 2
#70000
b11111111111111111111111111110000 !
b11111111111111111111111111110000 5
b11111111111111111111111111110000 C
b11111111111111111111111111110000 K
b11111111111111111111111111110000 J
b11111111111111111111111100000000 I
b11111111111111111111111100000000 H
b1111111111111111 L
b11111111111111111111111100000000 /
b11111111111111111111111100000000 2
#80000
b1 !
b1 5
b1 C
b1010 1
b1010 4
b1100100 0
b1100100 3
b1100100 /
b1100100 2
#90000
b0 !
b0 5
b0 C
b1100011 0
b1100011 3
#100000
b1 !
b1 5
b1 C
b1011 1
b1011 4
b10010110 0
b10010110 3
b11001000 /
b11001000 2
#110000
b1100 1
b1100 4
b1100100 0
b1100100 3
b110010 /
b110010 2
#120000
b0 !
b0 5
b0 C
b11111 1
b11111 4
b0 0
b0 3
b0 /
b0 2
